customer_analysis/__main__.py
customer_analysis/report_generator.py
custiomer_analysis_bertollo-0.1.0.dist-info/METADATA
custiomer_analysis_bertollo-0.1.0.dist-info/WHEEL
custiomer_analysis_bertollo-0.1.0.dist-info/entry_points.txt
custiomer_analysis_bertollo-0.1.0.dist-info/top_level.txt
custiomer_analysis_bertollo-0.1.0.dist-info/RECORD
